pipc_flask_app/__init__.py
pipc_flask_app/flask_constants.py
pipc_flask_app/flask_func.py
pipc_flask_app/flaskapp.py
pipc_flask_app/framework.py
pipc_flask_app/images.py
pipc_flask_app/main.py
pipc_flask_app-0.1.0.dist-info/LICENSE
pipc_flask_app-0.1.0.dist-info/METADATA
pipc_flask_app-0.1.0.dist-info/WHEEL
pipc_flask_app-0.1.0.dist-info/entry_points.txt
pipc_flask_app-0.1.0.dist-info/top_level.txt
pipc_flask_app-0.1.0.dist-info/RECORD
