Metadata-Version: 2.1
Name: pipc_flask_app
Version: 0.1.0
Summary: A plugin to create flask app for pipCreator.
Author: Rakesh Kanna
Author-email: rakeshkanna0108@gmail.com
License: MIT
Keywords: plugin,flask,app,pipcreator
Classifier: Programming Language :: Python :: 3
Classifier: License :: OSI Approved :: MIT License
Classifier: Operating System :: OS Independent
Classifier: Framework :: Flask
Classifier: Topic :: Software Development :: Libraries :: Python Modules
Classifier: Topic :: Software Development :: Build Tools
Requires-Python: >=3.6
License-File: LICENSE
Requires-Dist: Flask==2.3.2
Requires-Dist: Flask-SQLAlchemy==3.0.3
Requires-Dist: Flask-Migrate==4.0.4
Requires-Dist: Flask-WTF==1.0.1
Requires-Dist: python-dotenv
Requires-Dist: pipCreator
